holo_search_sdk/__init__.py
holo_search_sdk/client.py
holo_search_sdk/exceptions.py
holo_search_sdk/types.py
holo_search_sdk/backend/__init__.py
holo_search_sdk/backend/connection.py
holo_search_sdk/backend/database.py
holo_search_sdk/backend/filter.py
holo_search_sdk/backend/query.py
holo_search_sdk/backend/table.py
holo_search_sdk/backend/utils/__init__.py
holo_search_sdk/backend/utils/sql_utils.py
holo_search_sdk-0.3.0.dist-info/LICENSE.txt
holo_search_sdk-0.3.0.dist-info/METADATA
holo_search_sdk-0.3.0.dist-info/WHEEL
holo_search_sdk-0.3.0.dist-info/top_level.txt
holo_search_sdk-0.3.0.dist-info/RECORD
