Metadata-Version: 2.1
Name: holo-search-sdk
Version: 0.3.0
Summary: A Python SDK for database search operations with vector and full-text search capabilities
Author-email: Tiancheng YANG <yangtiancheng.ytc@alibaba-inc.com>
License: MIT
Project-URL: Homepage, https://github.com/hologram/holo-search-sdk
Project-URL: Documentation, https://holo-search-sdk.readthedocs.io
Project-URL: Repository, https://github.com/hologram/holo-search-sdk
Project-URL: Issues, https://github.com/hologram/holo-search-sdk/issues
Classifier: Development Status :: 3 - Alpha
Classifier: Intended Audience :: Developers
Classifier: License :: OSI Approved :: MIT License
Classifier: Programming Language :: Python :: 3
Classifier: Programming Language :: Python :: 3.8
Classifier: Programming Language :: Python :: 3.9
Classifier: Programming Language :: Python :: 3.10
Classifier: Programming Language :: Python :: 3.11
Classifier: Programming Language :: Python :: 3.12
Requires-Python: >=3.8
License-File: LICENSE.txt
Requires-Dist: numpy>=1.20.0
Requires-Dist: typing-extensions>=4.0.0
Requires-Dist: psycopg[binary]>=3.2.0
Provides-Extra: dev
Requires-Dist: pytest>=7.0.0; extra == "dev"
Requires-Dist: pytest-asyncio>=0.21.0; extra == "dev"
Requires-Dist: pytest-cov>=4.0.0; extra == "dev"
Requires-Dist: black>=23.0.0; extra == "dev"
Requires-Dist: isort>=5.12.0; extra == "dev"
Requires-Dist: flake8>=6.0.0; extra == "dev"
Requires-Dist: mypy>=1.0.0; extra == "dev"
Requires-Dist: pre-commit>=3.0.0; extra == "dev"
